interactive_curve_fit/__init__.py
interactive_curve_fit/_version.py
interactive_curve_fit/core/__init__.py
interactive_curve_fit/core/fitter.py
interactive_curve_fit/core/fitter_old.py
interactive_curve_fit/core/fitting_functions.py
interactive_curve_fit/core/guessor.py
interactive_curve_fit/core/preprocessor.py
interactive_curve_fit/utils/__init__.py
interactive_curve_fit/utils/draw_test_data.py
interactive_curve_fit/utils/img_to_csv.py
interactive_curve_fit/utils/visualize.py
interactive_curve_fit-0.0.1.dist-info/LICENSE
interactive_curve_fit-0.0.1.dist-info/METADATA
interactive_curve_fit-0.0.1.dist-info/WHEEL
interactive_curve_fit-0.0.1.dist-info/top_level.txt
interactive_curve_fit-0.0.1.dist-info/RECORD
