Metadata-Version: 2.1
Name: interactive-curve-fit
Version: 0.0.1
Summary: interactive_curve_fit: A Python project enables you to do curve fitting on spectrum data interactively on GUI. You can visualize your spectrum and fit the optional number of peaks on GUI using Scipy.optimize.curve_fit method.
Home-page: https://github.com/passive-radio/interactive-curve-fit
Author: Yudai Okubo
Author-email: yudaiokubo@gmail.com
Maintainer: Yudai Okubo
Maintainer-email: yudaiokubo@gmail.com
License: MIT
Download-URL: https://github.com/passive-radio/interactive-curve-fit
Keywords: curve fit spectrum
Platform: UNKNOWN
Classifier: Programming Language :: Python :: 3
Classifier: License :: OSI Approved :: MIT License
Classifier: Operating System :: OS Independent
License-File: LICENSE
Requires-Dist: matplotlib (>=3.5.0)
Requires-Dist: numpy (>=1.21.4)
Requires-Dist: pandas (>=1.3.4)
Requires-Dist: Pillow (>=8.4.0)
Requires-Dist: scipy (>=1.7.3)
